basic_combinational/fullsub/fullsub.v
module full_subtractor(
    input A,
    input B,
    input Bin,
    output Difference,
    output Borrow
);

assign Difference = A ^ B ^ Bin;
assign Borrow = (~A & B) | (~A & Bin) | (B & Bin);

endmodule

basic_combinational/fullsub/fullsub_tb.v
`timescale 1ns/1ps

module full_subtractor_tb;

reg A;
reg B;
reg Bin;
wire Difference;
wire Borrow;

full_subtractor uut (
    .A(A),
    .B(B),
    .Bin(Bin),
    .Difference(Difference),
    .Borrow(Borrow)
);

initial begin
    $dumpfile("full_subtractor.vcd");
    $dumpvars(0, full_subtractor_tb);

    $display("Time\tA\tB\tBin\tDifference\tBorrow");
    $monitor("%0t\t%b\t%b\t%b\t%b\t\t%b",
              $time, A, B, Bin, Difference, Borrow);

    A=0; B=0; Bin=0; #10;
    A=0; B=0; Bin=1; #10;
    A=0; B=1; Bin=0; #10;
    A=0; B=1; Bin=1; #10;
    A=1; B=0; Bin=0; #10;
    A=1; B=0; Bin=1; #10;
    A=1; B=1; Bin=0; #10;
    A=1; B=1; Bin=1; #10;

    $finish;
end

endmodule

basic_combinational/fullsub/full_subtractor.vcd
$date
	Fri Jun  5 03:50:12 2026
$end
$version
	Icarus Verilog
$end
$timescale
	1ps
$end
$scope module full_subtractor_tb $end
$var wire 1 ! Difference $end
$var wire 1 " Borrow $end
$var reg 1 # A $end
$var reg 1 $ B $end
$var reg 1 % Bin $end
$scope module uut $end
$var wire 1 # A $end
$var wire 1 $ B $end
$var wire 1 % Bin $end
$var wire 1 " Borrow $end
$var wire 1 ! Difference $end
$upscope $end
$upscope $end
$enddefinitions $end
$comment Show the parameter values. $end
$dumpall
$end
#0
$dumpvars
0%
0$
0#
0"
0!
$end
#10000
1"
1!
1%
#20000
0%
1$
#30000
0!
1%
#40000
0"
1!
0%
0$
1#
#50000
0!
1%
#60000
0%
1$
#70000
1"
1!
1%
