basic_combinational/mux81/mux81.v
module mux8to1(
    input [7:0] i,
    input [2:0] s,
    output y
);

assign y = i[s];

endmodule

basic_combinational/mux81/mux81_tb.v
module mux8to1_tb;

reg [7:0] i;
reg [2:0] s;
wire y;

mux8to1 uut (
    .i(i),
    .s(s),
    .y(y)
);

initial begin
    $dumpfile("mux8to1.vcd");
    $dumpvars(0, mux8to1_tb);

    i = 8'b10101010;

    s = 3'b000; #10;
    s = 3'b001; #10;
    s = 3'b010; #10;
    s = 3'b011; #10;
    s = 3'b100; #10;
    s = 3'b101; #10;
    s = 3'b110; #10;
    s = 3'b111; #10;

    $finish;
end

endmodule

basic_combinational/mux81/mux8to1.vcd
$date
	Tue Jun  9 03:31:45 2026
$end
$version
	Icarus Verilog
$end
$timescale
	1s
$end
$scope module mux8to1_tb $end
$var wire 1 ! y $end
$var reg 8 " i [7:0] $end
$var reg 3 # s [2:0] $end
$scope module uut $end
$var wire 8 $ i [7:0] $end
$var wire 3 % s [2:0] $end
$var wire 1 ! y $end
$upscope $end
$upscope $end
$enddefinitions $end
$comment Show the parameter values. $end
$dumpall
$end
#0
$dumpvars
b0 %
b10101010 $
b0 #
b10101010 "
0!
$end
#10
1!
b1 #
b1 %
#20
0!
b10 #
b10 %
#30
1!
b11 #
b11 %
#40
0!
b100 #
b100 %
#50
1!
b101 #
b101 %
#60
0!
b110 #
b110 %
#70
1!
b111 #
b111 %
