basic_combinational/mux21/mux21.v
module mux2to1(
    input a,
    input b,
    input sel,
    output y
);

assign y = sel ? b : a;

endmodule

basic_combinational/mux21/mux21_tb.v
`timescale 1ns/1ps

module mux2to1_tb;

reg a;
reg b;
reg sel;
wire y;

mux2to1 uut (
    .a(a),
    .b(b),
    .sel(sel),
    .y(y)
);

initial begin
    $dumpfile("mux2to1.vcd");
    $dumpvars(0, mux2to1_tb);

    $display("Time\tA\tB\tSEL\tY");
    $monitor("%0t\t%b\t%b\t%b\t%b",
              $time, a, b, sel, y);

    a=0; b=0; sel=0; #10;
    a=0; b=1; sel=0; #10;
    a=1; b=0; sel=0; #10;
    a=1; b=1; sel=0; #10;

    a=0; b=0; sel=1; #10;
    a=0; b=1; sel=1; #10;
    a=1; b=0; sel=1; #10;
    a=1; b=1; sel=1; #10;

    $finish;
end

endmodule

basic_combinational/mux21/mux2to1.vcd
$date
	Fri Jun  5 04:20:48 2026
$end
$version
	Icarus Verilog
$end
$timescale
	1ps
$end
$scope module mux2to1_tb $end
$var wire 1 ! y $end
$var reg 1 " a $end
$var reg 1 # b $end
$var reg 1 $ sel $end
$scope module uut $end
$var wire 1 " a $end
$var wire 1 # b $end
$var wire 1 $ sel $end
$var wire 1 ! y $end
$upscope $end
$upscope $end
$enddefinitions $end
$comment Show the parameter values. $end
$dumpall
$end
#0
$dumpvars
0$
0#
0"
0!
$end
#10000
1#
#20000
1!
0#
1"
#30000
1#
#40000
0!
1$
0#
0"
#50000
1!
1#
#60000
0!
0#
1"
#70000
1!
1#
