fsm_project/home_automation/home_automation.v
// smart_home_automation.v

module smart_home_automation (
    rst,
    clk,
    motion_detected,
    ambient_dark,
    temp_high,
    smoke_detected,
    arm_security,
    disarm_security,
    lights_on,
    fan_on,
    alarm_on,
    hvac_on,
    security_armed
);

// Inputs
input wire clk;
input wire rst;
input wire motion_detected;
input wire ambient_dark;
input wire temp_high;
input wire smoke_detected;
input wire arm_security;
input wire disarm_security;

// Outputs
output reg lights_on;
output reg fan_on;
output reg alarm_on;
output reg hvac_on;
output reg security_armed;

// State Encoding
parameter S_IDLE       = 3'b000,
          S_OCCUPIED   = 3'b001,
          S_NIGHT      = 3'b010,
          S_COOLING    = 3'b011,
          S_AWAY_ARMED = 3'b100,
          S_ALERT      = 3'b101;

reg [2:0] present_state, next_state;

// Present State Logic
always @(posedge clk or posedge rst)
begin
    if (rst)
        present_state <= S_IDLE;
    else
        present_state <= next_state;
end

// Next State Logic
always @(*)
begin
    next_state = present_state;

    if (smoke_detected)
    begin
        next_state = S_ALERT;
    end
    else
    begin
        case (present_state)

            S_IDLE:
            begin
                if (motion_detected)
                    next_state = S_OCCUPIED;
                else
                    next_state = S_IDLE;
            end

            S_OCCUPIED:
            begin
                if (!motion_detected)
                    next_state = S_IDLE;
                else if (ambient_dark)
                    next_state = S_NIGHT;
                else if (temp_high)
                    next_state = S_COOLING;
                else if (arm_security)
                    next_state = S_AWAY_ARMED;
                else
                    next_state = S_OCCUPIED;
            end

            S_NIGHT:
            begin
                if (!ambient_dark)
                    next_state = S_OCCUPIED;
                else if (!motion_detected)
                    next_state = S_IDLE;
                else
                    next_state = S_NIGHT;
            end

            S_COOLING:
            begin
                if (!temp_high)
                    next_state = S_OCCUPIED;
                else
                    next_state = S_COOLING;
            end

            S_AWAY_ARMED:
            begin
                if (disarm_security)
                    next_state = S_IDLE;
                else if (motion_detected)
                    next_state = S_ALERT;
                else
                    next_state = S_AWAY_ARMED;
            end

            S_ALERT:
            begin
                if (!smoke_detected && disarm_security && motion_detected)
                    next_state = S_OCCUPIED;
                else if (!smoke_detected && disarm_security && !motion_detected)
                    next_state = S_IDLE;
                else
                    next_state = S_ALERT;
            end

            default:
              next_state = S_IDLE;

        endcase
    end
end

// Output Logic
always @(*)
begin
    lights_on      = 1'b0;
    fan_on         = 1'b0;
    hvac_on        = 1'b0;
    alarm_on       = 1'b0;
    security_armed = 1'b0;

    if (!rst)
    begin
        case (present_state)

            S_NIGHT:
            begin
                lights_on = 1'b1;
            end

            S_COOLING:
            begin
                fan_on  = 1'b1;
                hvac_on = 1'b1;
            end

            S_ALERT:
            begin
                alarm_on = 1'b1;
            end

            S_AWAY_ARMED:
            begin
                security_armed = 1'b1;
            end

            default:
            begin
                lights_on      = 1'b0;
                fan_on         = 1'b0;
                hvac_on        = 1'b0;
                alarm_on       = 1'b0;
                security_armed = 1'b0;
            end

        endcase
    end
end

endmodule

fsm_project/home_automation/home_automation_tb.v
`timescale 1ns/1ps

module tb_smart_home_automation;

// Inputs
reg clk;
reg rst;
reg motion_detected;
reg ambient_dark;
reg temp_high;
reg smoke_detected;
reg arm_security;
reg disarm_security;

// Outputs
wire lights_on;
wire fan_on;
wire alarm_on;
wire hvac_on;
wire security_armed;

// DUT
smart_home_automation DUT (
    .clk(clk),
    .rst(rst),
    .motion_detected(motion_detected),
    .ambient_dark(ambient_dark),
    .temp_high(temp_high),
    .smoke_detected(smoke_detected),
    .arm_security(arm_security),
    .disarm_security(disarm_security),
    .lights_on(lights_on),
    .fan_on(fan_on),
    .alarm_on(alarm_on),
    .hvac_on(hvac_on),
    .security_armed(security_armed)
);

// Clock Generation
initial
begin
    clk = 0;
    forever #5 clk = ~clk;
end

// VCD Dump
initial
begin
    $dumpfile("smart_home_automation.vcd");
    $dumpvars(0, tb_smart_home_automation);
end

// Monitor
initial
begin
    $monitor(
        "T=%0t | State Outputs -> Light=%b Fan=%b HVAC=%b Alarm=%b Armed=%b",
        $time,
        lights_on,
        fan_on,
        hvac_on,
        alarm_on,
        security_armed
    );
end

// Test Stimulus
initial
begin
    // Reset
    rst = 1;
    motion_detected = 0;
    ambient_dark = 0;
    temp_high = 0;
    smoke_detected = 0;
    arm_security = 0;
    disarm_security = 0;

    #15 rst = 0;

    // IDLE -> OCCUPIED
    #10 motion_detected = 1;

    // OCCUPIED -> NIGHT
    #20 ambient_dark = 1;

    // NIGHT -> OCCUPIED
    #20 ambient_dark = 0;

    // OCCUPIED -> COOLING
    #20 temp_high = 1;

    // COOLING -> OCCUPIED
    #20 temp_high = 0;

    // OCCUPIED -> AWAY_ARMED
    #20 begin
        arm_security = 1;
        motion_detected = 1;
    end

    #10 arm_security = 0;

    // Return to IDLE
    #20 motion_detected = 0;

    // Arm Security Again
    #20 arm_security = 1;
    #10 arm_security = 0;

    // Intrusion -> ALERT
    #20 motion_detected = 1;

    // Clear Intrusion
    #20 begin
        disarm_security = 1;
        motion_detected = 0;
    end

    #20 disarm_security = 0;

    // Smoke Alert
    #20 smoke_detected = 1;

    #20 begin
        smoke_detected = 0;
        disarm_security = 1;
    end

    #20 disarm_security = 0;

    #50;
    $finish;
end

endmodule

fsm_project/home_automation/smart_home_automation.vcd
$date
	Mon Jun 15 07:22:44 2026
$end
$version
	Icarus Verilog
$end
$timescale
	1ps
$end
$scope module tb_smart_home_automation $end
$var wire 1 ! security_armed $end
$var wire 1 " lights_on $end
$var wire 1 # hvac_on $end
$var wire 1 $ fan_on $end
$var wire 1 % alarm_on $end
$var reg 1 & ambient_dark $end
$var reg 1 ' arm_security $end
$var reg 1 ( clk $end
$var reg 1 ) disarm_security $end
$var reg 1 * motion_detected $end
$var reg 1 + rst $end
$var reg 1 , smoke_detected $end
$var reg 1 - temp_high $end
$scope module DUT $end
$var wire 1 & ambient_dark $end
$var wire 1 ' arm_security $end
$var wire 1 ( clk $end
$var wire 1 ) disarm_security $end
$var wire 1 * motion_detected $end
$var wire 1 + rst $end
$var wire 1 , smoke_detected $end
$var wire 1 - temp_high $end
$var parameter 3 . S_ALERT $end
$var parameter 3 / S_AWAY_ARMED $end
$var parameter 3 0 S_COOLING $end
$var parameter 3 1 S_IDLE $end
$var parameter 3 2 S_NIGHT $end
$var parameter 3 3 S_OCCUPIED $end
$var reg 1 % alarm_on $end
$var reg 1 $ fan_on $end
$var reg 1 # hvac_on $end
$var reg 1 " lights_on $end
$var reg 3 4 next_state [2:0] $end
$var reg 3 5 present_state [2:0] $end
$var reg 1 ! security_armed $end
$upscope $end
$upscope $end
$enddefinitions $end
$comment Show the parameter values. $end
$dumpall
b1 3
b10 2
b0 1
b11 0
b100 /
b101 .
$end
#0
$dumpvars
b0 5
b0 4
0-
0,
1+
0*
0)
0(
0'
0&
0%
0$
0#
0"
0!
$end
#5000
1(
#10000
0(
#15000
1(
0+
#20000
0(
#25000
b1 5
b1 4
1(
1*
#30000
0(
#35000
1(
#40000
0(
#45000
1"
b10 5
b10 4
1(
1&
#50000
0(
#55000
1(
#60000
0(
#65000
0"
b1 5
b1 4
1(
0&
#70000
0(
#75000
1(
#80000
0(
#85000
1#
1$
b11 5
b11 4
1(
1-
#90000
0(
#95000
1(
#100000
0(
#105000
0#
0$
b1 5
b1 4
1(
0-
#110000
0(
#115000
1(
#120000
0(
#125000
1!
b100 5
b101 4
1(
1'
#130000
0(
#135000
1%
0!
b101 5
b101 4
1(
0'
#140000
0(
#145000
1(
#150000
0(
#155000
1(
0*
#160000
0(
#165000
1(
#170000
0(
#175000
1(
1'
#180000
0(
#185000
1(
0'
#190000
0(
#195000
1(
#200000
0(
#205000
1(
1*
#210000
0(
#215000
1(
#220000
0(
#225000
0%
b0 5
b0 4
1(
0*
1)
#230000
0(
#235000
1(
#240000
0(
#245000
1(
0)
#250000
0(
#255000
1(
#260000
0(
#265000
1%
b101 5
b101 4
1(
1,
#270000
0(
#275000
1(
#280000
0(
#285000
0%
b0 5
b0 4
1(
1)
0,
#290000
0(
#295000
1(
#300000
0(
#305000
1(
0)
