sequential_circuits/Latches_and_Flipflops/srlatch/srlatch.v
module srlatch(input s, input r,output reg q );
always @(*)
begin 
if(s)
q = 1'b1;
else if(r)
q = 1'b0;
end
endmodule

sequential_circuits/Latches_and_Flipflops/srlatch/srlatch_tb.v
`timescale 1ns/1ps

module srlatch_tb;
reg s;
reg r;
wire q;

srlatch uut (.s(s),.r(r),.q(q));

initial
begin 
$dumpfile("srlatch.vcd");
$dumpvars(0,srlatch_tb);

s=0; r=0;
#10;

s=1;r=0;
#10;

s=0;r=0;
#10;

s=0;r=1;
#10;

s=0;r=0;
#10;
s = 1; r = 0;
#10;
 
s = 1; r = 1;
#10;

s = 0; r = 0;
#10;

$finish;
end

initial begin
    $monitor("Time=%0t s=%b r=%b q=%b", $time, s, r, q);
end

endmodule

sequential_circuits/Latches_and_Flipflops/srlatch/srlatch.vcd
$date
	Fri Jun 19 05:09:53 2026
$end
$version
	Icarus Verilog
$end
$timescale
	1ps
$end
$scope module srlatch_tb $end
$var wire 1 ! q $end
$var reg 1 " r $end
$var reg 1 # s $end
$scope module uut $end
$var wire 1 " r $end
$var wire 1 # s $end
$var reg 1 ! q $end
$upscope $end
$upscope $end
$enddefinitions $end
$comment Show the parameter values. $end
$dumpall
$end
#0
$dumpvars
0#
0"
x!
$end
#10000
1!
1#
#20000
0#
#30000
0!
1"
#40000
0"
#50000
1!
1#
#60000
1"
#70000
0"
0#
